<?xml version="1.0" encoding="utf-8"?>
<edmx:Edmx Version="4.0" xmlns:edmx="http://docs.oasis-open.org/odata/ns/edmx" xmlns="http://docs.oasis-open.org/odata/ns/edm">
    <edmx:Reference Uri="/sap/opu/odata/IWFND/CATALOGSERVICE;v=2/Vocabularies(TechnicalName='%2FIWBEP%2FVOC_COMMUNICATION',Version='0001',SAP__Origin='LOCAL')/$value">
        <edmx:Include Namespace="com.sap.vocabularies.Communication.v1" Alias="Communication"/>
    </edmx:Reference>
    <edmx:Reference Uri="/sap/opu/odata/IWFND/CATALOGSERVICE;v=2/Vocabularies(TechnicalName='%2FIWBEP%2FVOC_PERSONALDATA',Version='0001',SAP__Origin='LOCAL')/$value">
        <edmx:Include Namespace="com.sap.vocabularies.PersonalData.v1" Alias="PersonalData"/>
    </edmx:Reference>
    <edmx:Reference Uri="/sap/opu/odata/IWFND/CATALOGSERVICE;v=2/Vocabularies(TechnicalName='%2FIWBEP%2FVOC_ANALYTICS',Version='0001',SAP__Origin='LOCAL')/$value">
        <edmx:Include Namespace="com.sap.vocabularies.Analytics.v1" Alias="Analytics"/>
    </edmx:Reference>
    <edmx:Reference Uri="/sap/opu/odata/IWFND/CATALOGSERVICE;v=2/Vocabularies(TechnicalName='%2FIWBEP%2FVOC_AGGREGATION',Version='0001',SAP__Origin='LOCAL')/$value">
        <edmx:Include Namespace="Org.OData.Aggregation.V1" Alias="SAP__aggregation"/>
    </edmx:Reference>
    <edmx:Reference Uri="/sap/opu/odata/IWFND/CATALOGSERVICE;v=2/Vocabularies(TechnicalName='%2FIWBEP%2FVOC_CAPABILITIES',Version='0001',SAP__Origin='LOCAL')/$value">
        <edmx:Include Namespace="Org.OData.Capabilities.V1" Alias="SAP__capabilities"/>
    </edmx:Reference>
    <edmx:Reference Uri="/sap/opu/odata/IWFND/CATALOGSERVICE;v=2/Vocabularies(TechnicalName='%2FIWBEP%2FVOC_CODELIST',Version='0001',SAP__Origin='LOCAL')/$value">
        <edmx:Include Namespace="com.sap.vocabularies.CodeList.v1" Alias="SAP__CodeList"/>
    </edmx:Reference>
    <edmx:Reference Uri="/sap/opu/odata/IWFND/CATALOGSERVICE;v=2/Vocabularies(TechnicalName='%2FIWBEP%2FVOC_COMMON',Version='0001',SAP__Origin='LOCAL')/$value">
        <edmx:Include Namespace="com.sap.vocabularies.Common.v1" Alias="SAP__common"/>
    </edmx:Reference>
    <edmx:Reference Uri="/sap/opu/odata/IWFND/CATALOGSERVICE;v=2/Vocabularies(TechnicalName='%2FIWBEP%2FVOC_CORE',Version='0001',SAP__Origin='LOCAL')/$value">
        <edmx:Include Namespace="Org.OData.Core.V1" Alias="SAP__core"/>
    </edmx:Reference>
    <edmx:Reference Uri="/sap/opu/odata/IWFND/CATALOGSERVICE;v=2/Vocabularies(TechnicalName='%2FIWBEP%2FVOC_HIERARCHY',Version='0001',SAP__Origin='LOCAL')/$value">
        <edmx:Include Namespace="com.sap.vocabularies.Hierarchy.v1" Alias="SAP__hierarchy"/>
    </edmx:Reference>
    <edmx:Reference Uri="/sap/opu/odata/IWFND/CATALOGSERVICE;v=2/Vocabularies(TechnicalName='%2FIWBEP%2FVOC_HTML5',Version='0001',SAP__Origin='LOCAL')/$value">
        <edmx:Include Namespace="com.sap.vocabularies.HTML5.v1" Alias="SAP__HTML5"/>
    </edmx:Reference>
    <edmx:Reference Uri="/sap/opu/odata/IWFND/CATALOGSERVICE;v=2/Vocabularies(TechnicalName='%2FIWBEP%2FVOC_MEASURES',Version='0001',SAP__Origin='LOCAL')/$value">
        <edmx:Include Namespace="Org.OData.Measures.V1" Alias="SAP__measures"/>
    </edmx:Reference>
    <edmx:Reference Uri="/sap/opu/odata/IWFND/CATALOGSERVICE;v=2/Vocabularies(TechnicalName='%2FIWBEP%2FVOC_ODM',Version='0001',SAP__Origin='LOCAL')/$value">
        <edmx:Include Namespace="com.sap.vocabularies.ODM.v1" Alias="SAP__ODM"/>
    </edmx:Reference>
    <edmx:Reference Uri="/sap/opu/odata/IWFND/CATALOGSERVICE;v=2/Vocabularies(TechnicalName='%2FIWBEP%2FVOC_PDF',Version='0001',SAP__Origin='LOCAL')/$value">
        <edmx:Include Namespace="com.sap.vocabularies.PDF.v1" Alias="SAP__PDF"/>
    </edmx:Reference>
    <edmx:Reference Uri="/sap/opu/odata/IWFND/CATALOGSERVICE;v=2/Vocabularies(TechnicalName='%2FIWBEP%2FVOC_SESSION',Version='0001',SAP__Origin='LOCAL')/$value">
        <edmx:Include Namespace="com.sap.vocabularies.Session.v1" Alias="SAP__session"/>
    </edmx:Reference>
    <edmx:Reference Uri="/sap/opu/odata/IWFND/CATALOGSERVICE;v=2/Vocabularies(TechnicalName='%2FIWBEP%2FVOC_UI',Version='0001',SAP__Origin='LOCAL')/$value">
        <edmx:Include Namespace="com.sap.vocabularies.UI.v1" Alias="SAP__UI"/>
    </edmx:Reference>
    <edmx:Reference Uri="/sap/opu/odata/IWFND/CATALOGSERVICE;v=2/Vocabularies(TechnicalName='%2FIWBEP%2FVOC_VALIDATION',Version='0001',SAP__Origin='LOCAL')/$value">
        <edmx:Include Namespace="Org.OData.Validation.V1" Alias="SAP__validation"/>
    </edmx:Reference>
    <edmx:DataServices>
        <Schema Namespace="com.sap.gateway.srvd.zsd_rep_mr903.v0001" Alias="SAP__self">
            <Annotation Term="SAP__core.SchemaVersion" String="1.0.0"/>
            <EntityType Name="valueHelp02Type">
                <Key>
                    <PropertyRef Name="POItemName"/>
                    <PropertyRef Name="language"/>
                </Key>
                <Property Name="POItemName" Type="Edm.String" Nullable="false" MaxLength="1"/>
                <Property Name="language" Type="Edm.String" Nullable="false" MaxLength="2"/>
                <Property Name="Text" Type="Edm.String" Nullable="false" MaxLength="60"/>
            </EntityType>
            <EntityType Name="poListType">
                <Key>
                    <PropertyRef Name="PurchaseOrder"/>
                    <PropertyRef Name="PurchaseOrderItem"/>
                </Key>
                <Property Name="PurchaseOrder" Type="Edm.String" Nullable="false" MaxLength="10"/>
                <Property Name="PurchaseOrderItem" Type="Edm.String" Nullable="false" MaxLength="5"/>
                <Property Name="Material" Type="Edm.String" Nullable="false" MaxLength="18"/>
                <Property Name="ProductType" Type="Edm.String" Nullable="false" MaxLength="2"/>
                <Property Name="CompanyCode" Type="Edm.String" Nullable="false" MaxLength="4"/>
                <Property Name="Plant" Type="Edm.String" Nullable="false" MaxLength="4"/>
                <Property Name="PurchaseOrderQuantityUnit" Type="Edm.String" Nullable="false" MaxLength="3"/>
                <Property Name="NetPriceQuantity" Type="Edm.Decimal" Nullable="false" Precision="5"/>
                <Property Name="__OperationControl" Type="com.sap.gateway.srvd.zsd_rep_mr903.v0001.poListOperationControl"/>
                <Property Name="SAP__Messages" Type="Collection(com.sap.gateway.srvd.zsd_rep_mr903.v0001.SAP__Message)" Nullable="false"/>
            </EntityType>
            <EntityType Name="valueHelpType">
                <Key>
                    <PropertyRef Name="POItemName"/>
                    <PropertyRef Name="language"/>
                </Key>
                <Property Name="POItemName" Type="Edm.String" Nullable="false" MaxLength="1"/>
                <Property Name="language" Type="Edm.String" Nullable="false" MaxLength="2"/>
                <Property Name="Text" Type="Edm.String" Nullable="false" MaxLength="60"/>
            </EntityType>
            <ComplexType Name="poListOperationControl">
                <Property Name="svf_output" Type="Edm.Boolean" Nullable="false"/>
            </ComplexType>
            <ComplexType Name="ZA_MR903_01_VN">
                <Property Name="FormName" Type="Edm.String" Nullable="false" MaxLength="80"/>
                <Property Name="PONo" Type="Edm.String" Nullable="false" MaxLength="50"/>
                <Property Name="PONotes" Type="Edm.String" Nullable="false" MaxLength="40"/>
                <Property Name="PrinterName" Type="Edm.String" Nullable="false" MaxLength="50"/>
                <Property Name="PrintPosition1" Type="Edm.String" Nullable="false" MaxLength="1"/>
                <Property Name="PrintPosition2" Type="Edm.String" Nullable="false" MaxLength="1"/>
                <Property Name="PrintPosition3" Type="Edm.String" Nullable="false" MaxLength="1"/>
                <Property Name="SignersName" Type="Edm.String" Nullable="false" MaxLength="20"/>
                <Property Name="static_text" Type="Edm.String" Nullable="false" MaxLength="1"/>
            </ComplexType>
            <ComplexType Name="SAP__Message">
                <Property Name="code" Type="Edm.String" Nullable="false"/>
                <Property Name="message" Type="Edm.String" Nullable="false"/>
                <Property Name="target" Type="Edm.String"/>
                <Property Name="additionalTargets" Type="Collection(Edm.String)" Nullable="false"/>
                <Property Name="transition" Type="Edm.Boolean" Nullable="false"/>
                <Property Name="numericSeverity" Type="Edm.Byte" Nullable="false"/>
                <Property Name="longtextUrl" Type="Edm.String"/>
            </ComplexType>
            <Action Name="svf_output" IsBound="true">
                <Parameter Name="_it" Type="com.sap.gateway.srvd.zsd_rep_mr903.v0001.poListType" Nullable="false"/>
                <Parameter Name="PrinterName" Type="Edm.String" Nullable="false" MaxLength="50"/>
                <Parameter Name="FormName" Type="Edm.String" Nullable="false" MaxLength="80"/>
                <Parameter Name="SignersName" Type="Edm.String" Nullable="false" MaxLength="20"/>
                <Parameter Name="PONotes" Type="Edm.String" Nullable="false" MaxLength="40"/>
                <Parameter Name="PONo" Type="Edm.String" Nullable="false" MaxLength="50"/>
                <Parameter Name="PrintPosition1" Type="Edm.String" Nullable="false" MaxLength="1"/>
                <Parameter Name="PrintPosition2" Type="Edm.String" Nullable="false" MaxLength="1"/>
                <Parameter Name="PrintPosition3" Type="Edm.String" Nullable="false" MaxLength="1"/>
                <Parameter Name="static_text" Type="Edm.String" Nullable="false" MaxLength="1"/>
                <ReturnType Type="com.sap.gateway.srvd.zsd_rep_mr903.v0001.ZA_MR903_01_VN" Nullable="false"/>
            </Action>
            <Function Name="GetDefaultsFor_ZA_MR903_01_VN" IsBound="true">
                <Parameter Name="_it" Type="com.sap.gateway.srvd.zsd_rep_mr903.v0001.poListType" Nullable="false"/>
                <ReturnType Type="com.sap.gateway.srvd.zsd_rep_mr903.v0001.ZA_MR903_01_VN" Nullable="false"/>
            </Function>
            <EntityContainer Name="Container">
                <EntitySet Name="poList" EntityType="com.sap.gateway.srvd.zsd_rep_mr903.v0001.poListType"/>
                <EntitySet Name="valueHelp" EntityType="com.sap.gateway.srvd.zsd_rep_mr903.v0001.valueHelpType"/>
                <EntitySet Name="valueHelp02" EntityType="com.sap.gateway.srvd.zsd_rep_mr903.v0001.valueHelp02Type"/>
            </EntityContainer>
            <Annotations Target="SAP__self.ZA_MR903_01_VN/FormName">
                <Annotation Term="SAP__common.Label" String="{@i18n&gt;FormName}"/>
            </Annotations>
            <Annotations Target="SAP__self.ZA_MR903_01_VN/PONo">
                <Annotation Term="SAP__common.Label" String="{@i18n&gt;PONo}"/>
            </Annotations>
            <Annotations Target="SAP__self.ZA_MR903_01_VN/PONotes">
                <Annotation Term="SAP__common.Label" String="{@i18n&gt;PONotes}"/>
            </Annotations>
            <Annotations Target="SAP__self.ZA_MR903_01_VN/PrinterName">
                <Annotation Term="SAP__common.Label" String="{@i18n&gt;PrinterName}"/>
            </Annotations>
            <Annotations Target="SAP__self.ZA_MR903_01_VN/PrintPosition1">
                <Annotation Term="SAP__common.Label" String="{@i18n&gt;PrintPosition1}"/>
                <Annotation Term="SAP__common.IsUpperCase"/>
            </Annotations>
            <Annotations Target="SAP__self.ZA_MR903_01_VN/PrintPosition2">
                <Annotation Term="SAP__common.Label" String="{@i18n&gt;PrintPosition2}"/>
                <Annotation Term="SAP__common.IsUpperCase"/>
            </Annotations>
            <Annotations Target="SAP__self.ZA_MR903_01_VN/PrintPosition3">
                <Annotation Term="SAP__common.Label" String="{@i18n&gt;PrintPosition3}"/>
                <Annotation Term="SAP__common.IsUpperCase"/>
            </Annotations>
            <Annotations Target="SAP__self.ZA_MR903_01_VN/SignersName">
                <Annotation Term="SAP__common.Label" String="{@i18n&gt;SignerName}"/>
            </Annotations>
            <Annotations Target="SAP__self.ZA_MR903_01_VN/static_text">
                <Annotation Term="SAP__common.Label" String="{@i18n&gt;PopUpInfoText}"/>
            </Annotations>
            <Annotations Target="SAP__self.valueHelp02Type/POItemName">
                <Annotation Term="SAP__common.IsUpperCase"/>
            </Annotations>
            <Annotations Target="SAP__self.valueHelp02Type">
                <Annotation Term="SAP__common.Label" String="ZI_MR903_05_VN"/>
            </Annotations>
            <Annotations Target="SAP__self.Container/valueHelp02">
                <Annotation Term="SAP__capabilities.SearchRestrictions">
                    <Record>
                        <PropertyValue Property="Searchable" Bool="false"/>
                    </Record>
                </Annotation>
                <Annotation Term="SAP__capabilities.InsertRestrictions">
                    <Record>
                        <PropertyValue Property="Insertable" Bool="false"/>
                    </Record>
                </Annotation>
                <Annotation Term="SAP__capabilities.DeleteRestrictions">
                    <Record>
                        <PropertyValue Property="Deletable" Bool="false"/>
                    </Record>
                </Annotation>
                <Annotation Term="SAP__capabilities.UpdateRestrictions">
                    <Record>
                        <PropertyValue Property="Updatable" Bool="false"/>
                        <PropertyValue Property="QueryOptions">
                            <Record>
                                <PropertyValue Property="SelectSupported" Bool="true"/>
                            </Record>
                        </PropertyValue>
                    </Record>
                </Annotation>
            </Annotations>
            <Annotations Target="SAP__self.poListType/PurchaseOrder">
                <Annotation Term="SAP__common.Label" String="{@i18n&gt;PurchaseOrder}"/>
                <Annotation Term="SAP__core.Computed"/>
                <Annotation Term="SAP__common.IsUpperCase"/>
                <Annotation Term="SAP__common.SemanticObject" String="PurchaseOrder"/>
                <Annotation Term="SAP__common.SemanticObjectMapping">
                    <Collection>
                        <Record>
                            <PropertyValue Property="LocalProperty" PropertyPath="PurchaseOrder"/>
                            <PropertyValue Property="SemanticObjectProperty" String="PurchaseOrder"/>
                        </Record>
                    </Collection>
                </Annotation>
                <Annotation Term="SAP__common.Heading" String="Purchase Order Number"/>
                <Annotation Term="SAP__common.QuickInfo" String="Purchase Order Number"/>
            </Annotations>
            <Annotations Target="SAP__self.poListType/PurchaseOrderItem">
                <Annotation Term="SAP__common.Label" String="{@i18n&gt;PurchaseOrderItem}"/>
                <Annotation Term="SAP__core.Computed"/>
                <Annotation Term="SAP__common.IsDigitSequence"/>
                <Annotation Term="SAP__common.Heading" String="Item Number of Purchase Order"/>
                <Annotation Term="SAP__common.QuickInfo" String="Item Number of Purchase Order"/>
            </Annotations>
            <Annotations Target="SAP__self.poListType/Material">
                <Annotation Term="SAP__common.Label" String="{@i18n&gt;Material}"/>
                <Annotation Term="SAP__common.IsUpperCase"/>
                <Annotation Term="SAP__common.Heading" String="Material"/>
                <Annotation Term="SAP__common.QuickInfo" String="Material Number"/>
                <Annotation Term="SAP__common.DocumentationRef" String="urn:sap-com:documentation:key?=type=DE&amp;id=MATNR"/>
            </Annotations>
            <Annotations Target="SAP__self.poListType/ProductType">
                <Annotation Term="SAP__common.Label" String="{@i18n&gt;ProductType}"/>
                <Annotation Term="SAP__common.IsUpperCase"/>
                <Annotation Term="SAP__common.Heading" String="Product Type Grp"/>
                <Annotation Term="SAP__common.QuickInfo" String="Product Type Group"/>
                <Annotation Term="SAP__common.DocumentationRef" String="urn:sap-com:documentation:key?=type=DE&amp;id=PRODUCT_TYPE"/>
            </Annotations>
            <Annotations Target="SAP__self.poListType/CompanyCode">
                <Annotation Term="SAP__common.Label" String="{@i18n&gt;CompanyCode}"/>
                <Annotation Term="SAP__common.IsUpperCase"/>
                <Annotation Term="SAP__common.Heading" String="CoCd"/>
                <Annotation Term="SAP__common.QuickInfo" String="Company Code"/>
                <Annotation Term="SAP__common.DocumentationRef" String="urn:sap-com:documentation:key?=type=DE&amp;id=BUKRS"/>
            </Annotations>
            <Annotations Target="SAP__self.poListType/Plant">
                <Annotation Term="SAP__common.Label" String="{@i18n&gt;Plant}"/>
                <Annotation Term="SAP__common.IsUpperCase"/>
                <Annotation Term="SAP__common.Heading" String="Plnt"/>
                <Annotation Term="SAP__common.QuickInfo" String="Plant"/>
                <Annotation Term="SAP__common.DocumentationRef" String="urn:sap-com:documentation:key?=type=DE&amp;id=EWERK"/>
            </Annotations>
            <Annotations Target="SAP__self.poListType/PurchaseOrderQuantityUnit">
                <Annotation Term="SAP__common.IsUnit"/>
                <Annotation Term="SAP__common.Label" String="{@i18n&gt;PurchaseOrderQuantityUnit}"/>
                <Annotation Term="SAP__common.Heading" String="OUn"/>
                <Annotation Term="SAP__common.QuickInfo" String="Purchase Order Unit of Measure"/>
                <Annotation Term="SAP__common.DocumentationRef" String="urn:sap-com:documentation:key?=type=DE&amp;id=BSTME"/>
            </Annotations>
            <Annotations Target="SAP__self.poListType/NetPriceQuantity">
                <Annotation Term="SAP__common.Label" String="{@i18n&gt;NetPriceQuantity}"/>
                <Annotation Term="SAP__common.Heading" String="Per"/>
                <Annotation Term="SAP__common.QuickInfo" String="Price Unit"/>
            </Annotations>
            <Annotations Target="SAP__self.poListType/__OperationControl">
                <Annotation Term="SAP__core.Computed"/>
                <Annotation Term="SAP__UI.HiddenFilter"/>
                <Annotation Term="SAP__UI.Hidden"/>
            </Annotations>
            <Annotations Target="SAP__self.svf_output(SAP__self.poListType)/PrinterName">
                <Annotation Term="SAP__common.Label" String="{@i18n&gt;PrinterName}"/>
                <Annotation Term="SAP__common.FieldControl" EnumMember="SAP__common.FieldControlType/Mandatory"/>
                <Annotation Term="SAP__UI.ParameterDefaultValue" String="PDF"/>
            </Annotations>
            <Annotations Target="SAP__self.svf_output(SAP__self.poListType)/FormName">
                <Annotation Term="SAP__common.Label" String="{@i18n&gt;FormName}"/>
                <Annotation Term="SAP__common.FieldControl" EnumMember="SAP__common.FieldControlType/Mandatory"/>
                <Annotation Term="SAP__UI.ParameterDefaultValue" String="MR903_01.xml"/>
            </Annotations>
            <Annotations Target="SAP__self.svf_output(SAP__self.poListType)/SignersName">
                <Annotation Term="SAP__common.Label" String="{@i18n&gt;SignerName}"/>
            </Annotations>
            <Annotations Target="SAP__self.svf_output(SAP__self.poListType)/PONotes">
                <Annotation Term="SAP__common.Label" String="{@i18n&gt;PONotes}"/>
            </Annotations>
            <Annotations Target="SAP__self.svf_output(SAP__self.poListType)/PONo">
                <Annotation Term="SAP__common.Label" String="{@i18n&gt;PONo}"/>
            </Annotations>
            <Annotations Target="SAP__self.svf_output(SAP__self.poListType)/PrintPosition1">
                <Annotation Term="SAP__common.Label" String="{@i18n&gt;PrintPosition1}"/>
                <Annotation Term="SAP__common.FieldControl" EnumMember="SAP__common.FieldControlType/Mandatory"/>
                <Annotation Term="SAP__common.IsUpperCase"/>
                <Annotation Term="SAP__common.ValueListReferences">
                    <Collection>
                        <String>../../../../srvd_f4/sap/zi_mr903_04_vn/0001;ps='srvd-zsd_rep_mr903-0001';va='com.sap.gateway.srvd.zsd_rep_mr903.v0001.ae-zc_mr903_01_vn.svf_output.printposition1.poListType'/$metadata</String>
                    </Collection>
                </Annotation>
                <Annotation Term="SAP__common.ValueListWithFixedValues"/>
            </Annotations>
            <Annotations Target="SAP__self.svf_output(SAP__self.poListType)/PrintPosition2">
                <Annotation Term="SAP__common.Label" String="{@i18n&gt;PrintPosition2}"/>
                <Annotation Term="SAP__common.FieldControl" EnumMember="SAP__common.FieldControlType/Mandatory"/>
                <Annotation Term="SAP__common.IsUpperCase"/>
                <Annotation Term="SAP__common.ValueListReferences">
                    <Collection>
                        <String>../../../../srvd_f4/sap/zi_mr903_04_vn/0001;ps='srvd-zsd_rep_mr903-0001';va='com.sap.gateway.srvd.zsd_rep_mr903.v0001.ae-zc_mr903_01_vn.svf_output.printposition2.poListType'/$metadata</String>
                    </Collection>
                </Annotation>
                <Annotation Term="SAP__common.ValueListWithFixedValues"/>
            </Annotations>
            <Annotations Target="SAP__self.svf_output(SAP__self.poListType)/PrintPosition3">
                <Annotation Term="SAP__common.Label" String="{@i18n&gt;PrintPosition3}"/>
                <Annotation Term="SAP__common.FieldControl" EnumMember="SAP__common.FieldControlType/Mandatory"/>
                <Annotation Term="SAP__common.IsUpperCase"/>
                <Annotation Term="SAP__common.ValueListReferences">
                    <Collection>
                        <String>../../../../srvd_f4/sap/zi_mr903_04_vn/0001;ps='srvd-zsd_rep_mr903-0001';va='com.sap.gateway.srvd.zsd_rep_mr903.v0001.ae-zc_mr903_01_vn.svf_output.printposition3.poListType'/$metadata</String>
                    </Collection>
                </Annotation>
                <Annotation Term="SAP__common.ValueListWithFixedValues"/>
            </Annotations>
            <Annotations Target="SAP__self.svf_output(SAP__self.poListType)/static_text">
                <Annotation Term="SAP__common.Label" String="{@i18n&gt;PopUpInfoText}"/>
            </Annotations>
            <Annotations Target="SAP__self.svf_output(SAP__self.poListType)">
                <Annotation Term="SAP__core.OperationAvailable" Path="_it/__OperationControl/svf_output"/>
                <Annotation Term="SAP__common.DefaultValuesFunction" String="com.sap.gateway.srvd.zsd_rep_mr903.v0001.GetDefaultsFor_ZA_MR903_01_VN"/>
            </Annotations>
            <Annotations Target="SAP__self.poListType">
                <Annotation Term="SAP__common.Label" String="ZC_MR903_01_VN"/>
                <Annotation Term="SAP__UI.LineItem">
                    <Collection>
                        <Record Type="SAP__UI.DataField">
                            <PropertyValue Property="Value" Path="PurchaseOrder"/>
                        </Record>
                        <Record Type="SAP__UI.DataField">
                            <PropertyValue Property="Value" Path="NetPriceQuantity"/>
                        </Record>
                        <Record Type="SAP__UI.DataField">
                            <PropertyValue Property="Value" Path="PurchaseOrderQuantityUnit"/>
                        </Record>
                        <Record Type="SAP__UI.DataField">
                            <PropertyValue Property="Value" Path="Plant"/>
                        </Record>
                        <Record Type="SAP__UI.DataField">
                            <PropertyValue Property="Value" Path="CompanyCode"/>
                        </Record>
                        <Record Type="SAP__UI.DataField">
                            <PropertyValue Property="Value" Path="ProductType"/>
                        </Record>
                        <Record Type="SAP__UI.DataField">
                            <PropertyValue Property="Value" Path="Material"/>
                        </Record>
                        <Record Type="SAP__UI.DataField">
                            <PropertyValue Property="Value" Path="PurchaseOrderItem"/>
                        </Record>
                        <Record Type="SAP__UI.DataFieldForAction">
                            <PropertyValue Property="Label" String="SVFの出力"/>
                            <PropertyValue Property="Action" String="com.sap.gateway.srvd.zsd_rep_mr903.v0001.svf_output(com.sap.gateway.srvd.zsd_rep_mr903.v0001.poListType)"/>
                            <PropertyValue Property="InvocationGrouping" EnumMember="SAP__UI.OperationGroupingType/ChangeSet"/>
                        </Record>
                    </Collection>
                </Annotation>
                <Annotation Term="SAP__UI.SelectionFields">
                    <Collection>
                        <PropertyPath>PurchaseOrder</PropertyPath>
                    </Collection>
                </Annotation>
                <Annotation Term="SAP__common.Messages" Path="SAP__Messages"/>
            </Annotations>
            <Annotations Target="SAP__self.Container/poList">
                <Annotation Term="SAP__capabilities.SearchRestrictions">
                    <Record>
                        <PropertyValue Property="Searchable" Bool="false"/>
                    </Record>
                </Annotation>
                <Annotation Term="SAP__capabilities.FilterRestrictions">
                    <Record>
                        <PropertyValue Property="NonFilterableProperties">
                            <Collection>
                                <PropertyPath>__OperationControl</PropertyPath>
                            </Collection>
                        </PropertyValue>
                    </Record>
                </Annotation>
                <Annotation Term="SAP__capabilities.SortRestrictions">
                    <Record>
                        <PropertyValue Property="NonSortableProperties">
                            <Collection>
                                <PropertyPath>__OperationControl</PropertyPath>
                            </Collection>
                        </PropertyValue>
                    </Record>
                </Annotation>
                <Annotation Term="SAP__capabilities.InsertRestrictions">
                    <Record>
                        <PropertyValue Property="Insertable" Bool="false"/>
                    </Record>
                </Annotation>
                <Annotation Term="SAP__capabilities.DeleteRestrictions">
                    <Record>
                        <PropertyValue Property="Deletable" Bool="false"/>
                    </Record>
                </Annotation>
                <Annotation Term="SAP__capabilities.UpdateRestrictions">
                    <Record>
                        <PropertyValue Property="Updatable" Bool="false"/>
                        <PropertyValue Property="QueryOptions">
                            <Record>
                                <PropertyValue Property="SelectSupported" Bool="true"/>
                            </Record>
                        </PropertyValue>
                    </Record>
                </Annotation>
            </Annotations>
            <Annotations Target="SAP__self.Container">
                <Annotation Term="SAP__CodeList.UnitsOfMeasure">
                    <Record>
                        <PropertyValue Property="Url" String="../../../../default/iwbep/common/0001/$metadata"/>
                        <PropertyValue Property="CollectionPath" String="UnitsOfMeasure"/>
                    </Record>
                </Annotation>
                <Annotation Term="SAP__common.ApplyMultiUnitBehaviorForSortingAndFiltering" Bool="true"/>
                <Annotation Term="SAP__capabilities.FilterFunctions">
                    <Collection>
                        <String>eq</String>
                        <String>ne</String>
                        <String>gt</String>
                        <String>ge</String>
                        <String>lt</String>
                        <String>le</String>
                        <String>and</String>
                        <String>or</String>
                        <String>contains</String>
                        <String>startswith</String>
                        <String>endswith</String>
                        <String>any</String>
                        <String>all</String>
                    </Collection>
                </Annotation>
                <Annotation Term="SAP__capabilities.SupportedFormats">
                    <Collection>
                        <String>application/json</String>
                        <String>application/pdf</String>
                    </Collection>
                </Annotation>
                <Annotation Term="SAP__PDF.Features">
                    <Record>
                        <PropertyValue Property="DocumentDescriptionReference" String="../../../../default/iwbep/common/0001/$metadata"/>
                        <PropertyValue Property="DocumentDescriptionCollection" String="MyDocumentDescriptions"/>
                        <PropertyValue Property="ArchiveFormat" Bool="true"/>
                        <PropertyValue Property="Border" Bool="true"/>
                        <PropertyValue Property="CoverPage" Bool="true"/>
                        <PropertyValue Property="FitToPage" Bool="true"/>
                        <PropertyValue Property="FontName" Bool="true"/>
                        <PropertyValue Property="FontSize" Bool="true"/>
                        <PropertyValue Property="HeaderFooter" Bool="true"/>
                        <PropertyValue Property="IANATimezoneFormat" Bool="true"/>
                        <PropertyValue Property="Margin" Bool="true"/>
                        <PropertyValue Property="Padding" Bool="true"/>
                        <PropertyValue Property="ResultSizeDefault" Int="20000"/>
                        <PropertyValue Property="ResultSizeMaximum" Int="20000"/>
                        <PropertyValue Property="Signature" Bool="true"/>
                        <PropertyValue Property="TextDirectionLayout" Bool="true"/>
                        <PropertyValue Property="Treeview" Bool="true"/>
                        <PropertyValue Property="UploadToFileShare" Bool="true"/>
                    </Record>
                </Annotation>
                <Annotation Term="SAP__capabilities.KeyAsSegmentSupported"/>
                <Annotation Term="SAP__capabilities.AsynchronousRequestsSupported"/>
            </Annotations>
            <Annotations Target="SAP__self.valueHelpType/POItemName">
                <Annotation Term="SAP__common.IsUpperCase"/>
            </Annotations>
            <Annotations Target="SAP__self.valueHelpType">
                <Annotation Term="SAP__common.Label" String="注文品目名"/>
            </Annotations>
            <Annotations Target="SAP__self.Container/valueHelp">
                <Annotation Term="SAP__capabilities.SearchRestrictions">
                    <Record>
                        <PropertyValue Property="Searchable" Bool="false"/>
                    </Record>
                </Annotation>
                <Annotation Term="SAP__capabilities.InsertRestrictions">
                    <Record>
                        <PropertyValue Property="Insertable" Bool="false"/>
                    </Record>
                </Annotation>
                <Annotation Term="SAP__capabilities.DeleteRestrictions">
                    <Record>
                        <PropertyValue Property="Deletable" Bool="false"/>
                    </Record>
                </Annotation>
                <Annotation Term="SAP__capabilities.UpdateRestrictions">
                    <Record>
                        <PropertyValue Property="Updatable" Bool="false"/>
                        <PropertyValue Property="QueryOptions">
                            <Record>
                                <PropertyValue Property="SelectSupported" Bool="true"/>
                            </Record>
                        </PropertyValue>
                    </Record>
                </Annotation>
            </Annotations>
            <Annotations Target="SAP__self.valueHelpType/language">
                <Annotation Term="SAP__UI.Hidden"/>
                <Annotation Term="SAP__common.Label" String="Lang."/>
                <Annotation Term="SAP__common.Heading" String="Ln"/>
                <Annotation Term="SAP__common.QuickInfo" String="Language Key"/>
                <Annotation Term="SAP__common.DocumentationRef" String="urn:sap-com:documentation:key?=type=DE&amp;id=DDLANGUAGE"/>
            </Annotations>
            <Annotations Target="SAP__self.valueHelp02Type/language">
                <Annotation Term="SAP__common.Label" String="Lang."/>
                <Annotation Term="SAP__common.Heading" String="Ln"/>
                <Annotation Term="SAP__common.QuickInfo" String="Language Key"/>
                <Annotation Term="SAP__common.DocumentationRef" String="urn:sap-com:documentation:key?=type=DE&amp;id=DDLANGUAGE"/>
            </Annotations>
            <Annotations Target="SAP__self.valueHelp02Type/Text">
                <Annotation Term="SAP__common.Label" String="Short Description"/>
                <Annotation Term="SAP__common.QuickInfo" String="Short Text for Fixed Values"/>
                <Annotation Term="SAP__common.DocumentationRef" String="urn:sap-com:documentation:key?=type=DE&amp;id=VAL_TEXT"/>
            </Annotations>
            <Annotations Target="SAP__self.valueHelpType/Text">
                <Annotation Term="SAP__common.Label" String="Short Description"/>
                <Annotation Term="SAP__common.QuickInfo" String="Short Text for Fixed Values"/>
                <Annotation Term="SAP__common.DocumentationRef" String="urn:sap-com:documentation:key?=type=DE&amp;id=VAL_TEXT"/>
            </Annotations>
            <Annotations Target="SAP__self.poListOperationControl/svf_output">
                <Annotation Term="SAP__common.Label" String="Dyn. Action Control"/>
                <Annotation Term="SAP__common.Heading" String="Dynamic Action Control"/>
                <Annotation Term="SAP__common.QuickInfo" String="Dynamic Action Property"/>
            </Annotations>
        </Schema>
    </edmx:DataServices>
</edmx:Edmx>